collective.zamqp-0.16.2-py2.7-nspkg.pth
collective/zamqp/__init__.py
collective/zamqp/changelog.txt
collective/zamqp/cli.py
collective/zamqp/component.xml
collective/zamqp/configure.zcml
collective/zamqp/connection.py
collective/zamqp/connection.txt
collective/zamqp/consumer.py
collective/zamqp/consumer.txt
collective/zamqp/datatypes.py
collective/zamqp/handlers.py
collective/zamqp/index.rst
collective/zamqp/index.txt
collective/zamqp/interfaces.py
collective/zamqp/introduction.rst
collective/zamqp/keepalive.py
collective/zamqp/message.py
collective/zamqp/message.txt
collective/zamqp/producer.py
collective/zamqp/publisher.py
collective/zamqp/publisher.txt
collective/zamqp/rabbitmq.rst
collective/zamqp/reload.py
collective/zamqp/reload.zcml
collective/zamqp/serializers.py
collective/zamqp/server.py
collective/zamqp/service.txt
collective/zamqp/testing.py
collective/zamqp/testing.zcml
collective/zamqp/testing_utilities.py
collective/zamqp/transactionmanager.py
collective/zamqp/utils.py
collective/zamqp/tests/__init__.py
collective/zamqp/tests/connection.txt
collective/zamqp/tests/consumer.txt
collective/zamqp/tests/consumerset.txt
collective/zamqp/tests/message.txt
collective/zamqp/tests/publisher.txt
collective/zamqp/tests/service_configure.txt
collective/zamqp/tests/service_consume.txt
collective/zamqp/tests/test_layer.py
collective/zamqp/tests/test_pickle_serializer.py
collective/zamqp/tests/test_plone_transaction.py
collective.zamqp-0.16.2.dist-info/DESCRIPTION.rst
collective.zamqp-0.16.2.dist-info/METADATA
collective.zamqp-0.16.2.dist-info/RECORD
collective.zamqp-0.16.2.dist-info/WHEEL
collective.zamqp-0.16.2.dist-info/entry_points.txt
collective.zamqp-0.16.2.dist-info/metadata.json
collective.zamqp-0.16.2.dist-info/namespace_packages.txt
collective.zamqp-0.16.2.dist-info/top_level.txt
