Metadata-Version: 2.0
Name: collective.zamqp
Version: 0.16.2
Summary: Asynchronous AMQP-integration for Plone (and Zope2)
Home-page: http://github.com/collective/collective.zamqp
Author: Asko Soukka
Author-email: asko.soukka@iki.fi
License: ZPL
Platform: UNKNOWN
Classifier: Operating System :: OS Independent
Classifier: Intended Audience :: Developers
Classifier: Topic :: Communications
Classifier: Topic :: System :: Distributed Computing
Classifier: Programming Language :: Python
Requires-Dist: setuptools
Requires-Dist: Zope2
Requires-Dist: ZODB3
Requires-Dist: transaction
Requires-Dist: zope.interface
Requires-Dist: zope.component
Requires-Dist: zope.publisher
Requires-Dist: zope.event
Requires-Dist: zope.processlifetime
Requires-Dist: grokcore.component
Requires-Dist: pika (==0.9.5)
Requires-Dist: collective.monkeypatcher (>=1.1.1)
Requires-Dist: zope.deprecation
Provides-Extra: docs
Requires-Dist: sphinx; extra == 'docs'
Requires-Dist: collective.sphinx.includedoc; extra == 'docs'
Requires-Dist: repoze.sphinx.autointerface; extra == 'docs'
Requires-Dist: sphinxcontrib-plantuml; extra == 'docs'
Requires-Dist: sphinxtogithub; extra == 'docs'
Provides-Extra: reload
Requires-Dist: z3c.unconfigure (==1.0.1); extra == 'reload'
Provides-Extra: test
Requires-Dist: testfixtures; extra == 'test'
Requires-Dist: rabbitfixture; extra == 'test'
Requires-Dist: plone.testing; extra == 'test'
Requires-Dist: plone.app.testing; extra == 'test'
Requires-Dist: zope.configuration; extra == 'test'
Requires-Dist: msgpack-python; extra == 'test'
